Metadata-Version: 2.1
Name: s3fs
Version: 2024.6.1
Summary: Convenient Filesystem interface over S3
Home-page: http://github.com/fsspec/s3fs/
Maintainer: Martin Durant
Maintainer-email: mdurant@continuum.io
License: BSD
Keywords: s3,boto
Classifier: Development Status :: 4 - Beta
Classifier: Intended Audience :: Developers
Classifier: License :: OSI Approved :: BSD License
Classifier: Operating System :: OS Independent
Classifier: Programming Language :: Python :: 3.8
Classifier: Programming Language :: Python :: 3.9
Classifier: Programming Language :: Python :: 3.10
Classifier: Programming Language :: Python :: 3.11
Requires-Python: >= 3.8
License-File: LICENSE.txt
Requires-Dist: aiobotocore<3.0.0,>=2.5.4
Requires-Dist: fsspec==2024.6.1.*
Requires-Dist: aiohttp!=4.0.0a0,!=4.0.0a1
Provides-Extra: awscli
Requires-Dist: aiobotocore[awscli]<3.0.0,>=2.5.4; extra == "awscli"
Provides-Extra: boto3
Requires-Dist: aiobotocore[boto3]<3.0.0,>=2.5.4; extra == "boto3"
